protonfixes/__init__.py
protonfixes/checks.py
protonfixes/config.py
protonfixes/corefonts.py
protonfixes/debug.py
protonfixes/fix.py
protonfixes/logger.py
protonfixes/splash.py
protonfixes/util.py
protonfixes/gamefixes/105450.py
protonfixes/gamefixes/15700.py
protonfixes/gamefixes/15740.py
protonfixes/gamefixes/221380.py
protonfixes/gamefixes/224960.py
protonfixes/gamefixes/227320.py
protonfixes/gamefixes/242640.py
protonfixes/gamefixes/242920.py
protonfixes/gamefixes/24960.py
protonfixes/gamefixes/253230.py
protonfixes/gamefixes/261110.py
protonfixes/gamefixes/261510.py
protonfixes/gamefixes/2620.py
protonfixes/gamefixes/266840.py
protonfixes/gamefixes/268050.py
protonfixes/gamefixes/271590.py
protonfixes/gamefixes/287450.py
protonfixes/gamefixes/312450.py
protonfixes/gamefixes/377840.py
protonfixes/gamefixes/379720.py
protonfixes/gamefixes/38400.py
protonfixes/gamefixes/38410.py
protonfixes/gamefixes/388750.py
protonfixes/gamefixes/390710.py
protonfixes/gamefixes/409720.py
protonfixes/gamefixes/410900.py
protonfixes/gamefixes/424840.py
protonfixes/gamefixes/475150.py
protonfixes/gamefixes/480.py
protonfixes/gamefixes/493200.py
protonfixes/gamefixes/546050.py
protonfixes/gamefixes/6020.py
protonfixes/gamefixes/6030.py
protonfixes/gamefixes/8500.py
protonfixes/gamefixes/8800.py
protonfixes/gamefixes/__init__.py
protonfixes-1.0.16.data/data/static/index.html
protonfixes-1.0.16.dist-info/METADATA
protonfixes-1.0.16.dist-info/RECORD
protonfixes-1.0.16.dist-info/WHEEL
protonfixes-1.0.16.dist-info/top_level.txt
tests/__init__.py
tests/test_utils.py
