Metadata-Version: 2.1
Name: protonfixes
Version: 1.0.16
Summary: Python module for applying fixes at runtime for games not supported by Steam Proton
Home-page: https://github.com/simons-public/protonfixes
Author: Chris Simons
Author-email: chris@simonsmail.net
License: UNKNOWN
Keywords: proton steam winetricks protonfixes
Platform: UNKNOWN
Classifier: Development Status :: 3 - Alpha
Classifier: Topic :: Games/Entertainment
Classifier: Operating System :: POSIX :: Linux
Classifier: License :: OSI Approved :: BSD License
